govuk_template_base/__init__.py
govuk_template_base/admin.py
govuk_template_base/apps.py
govuk_template_base/context_processors.py
govuk_template_base/models.py
govuk_template_base/service_settings.py
govuk_template_base/setup_extensions.py
govuk_template_base/locale/cy/LC_MESSAGES/django.mo
govuk_template_base/locale/cy/LC_MESSAGES/django.po
govuk_template_base/locale/en_GB/LC_MESSAGES/django.mo
govuk_template_base/locale/en_GB/LC_MESSAGES/django.po
govuk_template_base/management/__init__.py
govuk_template_base/management/commands/__init__.py
govuk_template_base/management/commands/buildscss.py
govuk_template_base/management/commands/devserver.py
govuk_template_base/management/commands/startgovukapp.py
govuk_template_base/management/commands/govuk_template_base/README.rst
govuk_template_base/management/commands/govuk_template_base/__init__.py-tpl
govuk_template_base/management/commands/govuk_template_base/apps.py-tpl
govuk_template_base/management/commands/govuk_template_base/static/README.rst
govuk_template_base/management/commands/govuk_template_base/static-src/README.rst
govuk_template_base/management/commands/govuk_template_base/static-src/stylesheets/base-print.scss-tpl
govuk_template_base/management/commands/govuk_template_base/static-src/stylesheets/base.scss-tpl
govuk_template_base/management/commands/govuk_template_base/templates/README.rst
govuk_template_base/management/commands/govuk_template_base/templates/app_name.html
govuk_template_base/migrations/0001_initial.py
govuk_template_base/migrations/__init__.py
govuk_template_base/static/images/govuk_template_base/pagination-sprite-hover.png
govuk_template_base/static/images/govuk_template_base/pagination-sprite-hover@2x.png
govuk_template_base/static/images/govuk_template_base/pagination-sprite.png
govuk_template_base/static/images/govuk_template_base/pagination-sprite@2x.png
govuk_template_base/static-src/stylesheets/govuk_template_base/README.rst
django_govuk_template-0.8.dist-info/LICENSE.txt
django_govuk_template-0.8.dist-info/METADATA
django_govuk_template-0.8.dist-info/WHEEL
django_govuk_template-0.8.dist-info/top_level.txt
django_govuk_template-0.8.dist-info/RECORD
