Metadata-Version: 2.1
Name: django-govuk-template
Version: 0.8
Summary: Django app that builds `template` and `elements` components from the Government Digital Services style guide
Home-page: https://github.com/ministryofjustice/django-govuk-template
Author: Ministry of Justice
Author-email: dev@digital.justice.gov.uk
License: MIT
Keywords: django govuk template elements frontend toolkit
Platform: UNKNOWN
Classifier: Development Status :: 4 - Beta
Classifier: Framework :: Django
Classifier: Intended Audience :: Developers
Classifier: License :: OSI Approved :: MIT License
Classifier: Natural Language :: English
Classifier: Operating System :: OS Independent
Classifier: Programming Language :: Python :: 3
Classifier: Programming Language :: Python :: 3.5
Classifier: Programming Language :: Python :: 3.6
Classifier: Programming Language :: Python :: 3.7
Requires-Dist: django (>=1.11)
Provides-Extra: forms
Requires-Dist: django-govuk-forms ; extra == 'forms'
Provides-Extra: scss
Requires-Dist: libsass ; extra == 'scss'
Provides-Extra: watch
Requires-Dist: watchdog ; extra == 'watch'
